[
    {
        "campground_id": 1,
        "origin_geo": "23.46427,120.55427",
        "geolocation": "23.3995944,120.5509358",
        "attaction_name": "綠盈牧場",
        "distance": "7.6 km"
    },
    {
        "campground_id": 1,
        "origin_geo": "23.46427,120.55427",
        "geolocation": "23.4654629,120.4801845",
        "attaction_name": "蘭潭月影潭心",
        "distance": "10.4 km"
    },
    {
        "campground_id": 1,
        "origin_geo": "23.46427,120.55427",
        "geolocation": "23.447201,120.49297",
        "attaction_name": "中埔穀倉農創園區",
        "distance": "8.0 km"
    }
]